configflow/__init__.py
configflow/core.py
configflow/parsers.py
configflow/validators.py
flow_config-0.1.0.dist-info/licenses/LICENSE
flow_config-0.1.0.dist-info/METADATA
flow_config-0.1.0.dist-info/WHEEL
flow_config-0.1.0.dist-info/top_level.txt
flow_config-0.1.0.dist-info/RECORD
