Metadata-Version: 2.4
Name: flow-config
Version: 0.1.0
Summary: A Python library for event-driven configuration management
Home-page: https://github.com/chinmay29hub/configflow
Author: Chinmay Sonawane
Author-email: Chinmay Sonawane <chinmaysonawane57@gmail.com>
License: MIT License
Project-URL: Homepage, https://github.com/chinmay29hub/configflow
Project-URL: Repository, https://github.com/chinmay29hub/configflow.git
Project-URL: Issues, https://github.com/chinmay29hub/configflow/issues
Project-URL: Documentation, https://configflow.readthedocs.io/
Requires-Python: >=3.9
License-File: LICENSE
Requires-Dist: watchdog>=2.0
Requires-Dist: PyYAML>=6.0
Requires-Dist: orjson>=3.0
Requires-Dist: pydantic>=2.0
Requires-Dist: python-dotenv>=1.1
Provides-Extra: dev
Requires-Dist: pytest>=7.0; extra == "dev"
Requires-Dist: black>=23.0; extra == "dev"
Requires-Dist: isort>=5.0; extra == "dev"
Requires-Dist: sphinx>=5.0; extra == "dev"
Requires-Dist: sphinx-rtd-theme>=1.0; extra == "dev"
Requires-Dist: myst-parser>=0.18; extra == "dev"
Requires-Dist: types-setuptools; extra == "dev"
Requires-Dist: types-PyYAML; extra == "dev"
Requires-Dist: pylint>=3.0; extra == "dev"
Requires-Dist: mypy>=1.0; extra == "dev"
Requires-Dist: python-dotenv>=1.1; extra == "dev"
Dynamic: author
Dynamic: home-page
Dynamic: license-file
Dynamic: requires-python
